amaas/__init__.py
amaas/grpc/__init__.py
amaas/grpc/util.py
amaas/grpc/aio/__init__.py
amaas/grpc/exception/__init__.py
amaas/grpc/protos/scan_pb2.py
amaas/grpc/protos/scan_pb2.pyi
amaas/grpc/protos/scan_pb2_grpc.py
visionone_filesecurity-1.4.2.dist-info/LICENSE
visionone_filesecurity-1.4.2.dist-info/METADATA
visionone_filesecurity-1.4.2.dist-info/NOTICE
visionone_filesecurity-1.4.2.dist-info/WHEEL
visionone_filesecurity-1.4.2.dist-info/top_level.txt
visionone_filesecurity-1.4.2.dist-info/RECORD
