Metadata-Version: 2.1
Name: visionone-filesecurity
Version: 1.4.2
Summary: Trend Micro VisionOne File Security SDK for python
Home-page: https://github.com/trendmicro/tm-v1-fs-python-sdk
Author: Trend Micro VisionOne File Security Team
Classifier: Programming Language :: Python
Classifier: Programming Language :: Python :: 3
Classifier: Programming Language :: Python :: 3.9
Classifier: Programming Language :: Python :: 3.10
Classifier: Programming Language :: Python :: 3.11
Classifier: Programming Language :: Python :: 3.12
Classifier: Programming Language :: Python :: 3.13
Classifier: License :: OSI Approved :: MIT License
Requires-Python: >=3.9, <=3.13
License-File: LICENSE
License-File: NOTICE
Requires-Dist: protobuf==5.29.4; python_version >= "3.8"
Requires-Dist: grpcio==1.71.0; python_version >= "3.9"
